{
	"format_version": "1.12.0",
	"minecraft:geometry": [
		{
			"description": {
				"identifier": "geometry.portal_delta",
				"texture_width": 256,
				"texture_height": 256,
				"visible_bounds_width": 13,
				"visible_bounds_height": 12,
				"visible_bounds_offset": [0, 4, 0]
			},
			"bones": [
				{
					"name": "bb_main",
					"pivot": [0, 0, 0],
					"locators": {
						"locator": [0, 64, -32],
						"name": [0, 58, -24]
					}
				},
				{
					"name": "bone",
					"pivot": [0, 64, -6]
				},
				{
					"name": "root",
					"parent": "bone",
					"pivot": [0, 64, -6],
					"cubes": [
						{
							"origin": [-64, 0, -6],
							"size": [128, 128, 0],
							"uv": {
								"north": {"uv": [0, 0], "uv_size": [128, 128]}
							}
						},
						{
							"origin": [-64, 0, -1],
							"size": [128, 128, 0],
							"pivot": [0, 64, -1],
							"rotation": [0, 180, 0],
							"uv": {
								"north": {"uv": [0, 0], "uv_size": [128, 128]}
							}
						}
					]
				},
				{
					"name": "root2",
					"parent": "bone",
					"pivot": [0, 64, 0],
					"rotation": [0, 0, 67.5],
					"cubes": [
						{
							"origin": [-60, 0, 1],
							"size": [128, 128, 0],
							"uv": {
								"north": {"uv": [0, 0], "uv_size": [128, 128]}
							}
						}
					]
				},
				{
					"name": "root3",
					"parent": "bone",
					"pivot": [0, 59, 6],
					"rotation": [0, 0, 45],
					"cubes": [
						{
							"origin": [-64, -5, 7],
							"size": [128, 128, 0],
							"uv": {
								"north": {"uv": [0, 0], "uv_size": [128, 128]}
							}
						}
					]
				},
				{
					"name": "HALO",
					"pivot": [0, 64, -7],
					"cubes": [
						{
							"origin": [-64, 0, -7],
							"size": [128, 128, 0],
							"uv": {
								"north": {"uv": [128, 0], "uv_size": [128, 128]}
							}
						}
					]
				},
				{
					"name": "LIGHT",
					"parent": "HALO",
					"pivot": [0, 52.86957, -7],
					"cubes": [
						{
							"origin": [-94.5, 40.5, -47],
							"size": [55, 0, 40],
							"pivot": [-47.5, 48.5, -15],
							"rotation": [0, 0, 90],
							"uv": {
								"up": {"uv": [245, 134], "uv_size": [2, 35]},
								"down": {"uv": [245, 169], "uv_size": [2, -35]}
							}
						},
						{
							"origin": [16.5, 40.5, -47],
							"size": [55, 0, 40],
							"pivot": [63.5, 48.5, -15],
							"rotation": [0, 0, 90],
							"uv": {
								"up": {"uv": [245, 134], "uv_size": [2, 35]},
								"down": {"uv": [245, 169], "uv_size": [2, -35]}
							}
						},
						{
							"origin": [-0.5, 55.5, -47],
							"size": [16, 0, 40],
							"pivot": [47.5, 63.5, -15],
							"rotation": [0, 0, 90],
							"uv": {
								"up": {"uv": [245, 134], "uv_size": [2, 35]},
								"down": {"uv": [245, 169], "uv_size": [2, -35]}
							}
						},
						{
							"origin": [-79.5, 55.5, -47],
							"size": [16, 0, 40],
							"pivot": [-31.5, 63.5, -15],
							"rotation": [0, 0, 90],
							"uv": {
								"up": {"uv": [245, 134], "uv_size": [2, 35]},
								"down": {"uv": [245, 169], "uv_size": [2, -35]}
							}
						},
						{
							"origin": [-63.5, 71.5, -47],
							"size": [16, 0, 40],
							"pivot": [-15.5, 79.5, -15],
							"rotation": [0, 0, 90],
							"uv": {
								"up": {"uv": [245, 134], "uv_size": [2, 35]},
								"down": {"uv": [245, 169], "uv_size": [2, -35]}
							}
						},
						{
							"origin": [-16.5, 71.5, -47],
							"size": [16, 0, 40],
							"pivot": [31.5, 79.5, -15],
							"rotation": [0, 0, 90],
							"uv": {
								"up": {"uv": [245, 134], "uv_size": [2, 35]},
								"down": {"uv": [245, 169], "uv_size": [2, -35]}
							}
						},
						{
							"origin": [-0.5, -15.5, -47],
							"size": [24, 0, 40],
							"pivot": [47.5, -7.5, -15],
							"rotation": [0, 0, 90],
							"uv": {
								"up": {"uv": [245, 134], "uv_size": [2, 35]},
								"down": {"uv": [245, 169], "uv_size": [2, -35]}
							}
						},
						{
							"origin": [-79.5, -15.5, -47],
							"size": [24, 0, 40],
							"pivot": [-31.5, -7.5, -15],
							"rotation": [0, 0, 90],
							"uv": {
								"up": {"uv": [245, 134], "uv_size": [2, 35]},
								"down": {"uv": [245, 169], "uv_size": [2, -35]}
							}
						},
						{
							"origin": [-55.5, -23.5, -47],
							"size": [8, 0, 40],
							"pivot": [-23.5, -15.5, -15],
							"rotation": [0, 0, 90],
							"uv": {
								"up": {"uv": [245, 134], "uv_size": [2, 35]},
								"down": {"uv": [245, 169], "uv_size": [2, -35]}
							}
						},
						{
							"origin": [7.5, -23.5, -47],
							"size": [8, 0, 40],
							"pivot": [39.5, -15.5, -15],
							"rotation": [0, 0, 90],
							"uv": {
								"up": {"uv": [245, 134], "uv_size": [2, 35]},
								"down": {"uv": [245, 169], "uv_size": [2, -35]}
							}
						},
						{
							"origin": [-0.5, -31.5, -47],
							"size": [8, 0, 40],
							"pivot": [31.5, -23.5, -15],
							"rotation": [0, 0, 90],
							"uv": {
								"up": {"uv": [245, 134], "uv_size": [2, 35]},
								"down": {"uv": [245, 169], "uv_size": [2, -35]}
							}
						},
						{
							"origin": [-47.5, -31.5, -47],
							"size": [8, 0, 40],
							"pivot": [-15.5, -23.5, -15],
							"rotation": [0, 0, 90],
							"uv": {
								"up": {"uv": [245, 134], "uv_size": [2, 35]},
								"down": {"uv": [245, 169], "uv_size": [2, -35]}
							}
						},
						{
							"origin": [39.5, 40.5, -47],
							"size": [16, 0, 40],
							"uv": {
								"up": {"uv": [245, 134], "uv_size": [2, 35]},
								"down": {"uv": [245, 169], "uv_size": [2, -35]}
							}
						},
						{
							"origin": [-55.5, 40.5, -47],
							"size": [16, 0, 40],
							"uv": {
								"up": {"uv": [245, 134], "uv_size": [2, 35]},
								"down": {"uv": [245, 169], "uv_size": [2, -35]}
							}
						},
						{
							"origin": [39.5, 95.5, -47],
							"size": [16, 0, 40],
							"uv": {
								"up": {"uv": [245, 134], "uv_size": [2, 35]},
								"down": {"uv": [245, 169], "uv_size": [2, -35]}
							}
						},
						{
							"origin": [23.5, 111.5, -47],
							"size": [16, 0, 40],
							"uv": {
								"up": {"uv": [245, 134], "uv_size": [2, 35]},
								"down": {"uv": [245, 169], "uv_size": [2, -35]}
							}
						},
						{
							"origin": [-39.5, 111.5, -47],
							"size": [16, 0, 40],
							"uv": {
								"up": {"uv": [245, 134], "uv_size": [2, 35]},
								"down": {"uv": [245, 169], "uv_size": [2, -35]}
							}
						},
						{
							"origin": [-55.5, 95.5, -47],
							"size": [16, 0, 40],
							"uv": {
								"up": {"uv": [245, 134], "uv_size": [2, 35]},
								"down": {"uv": [245, 169], "uv_size": [2, -35]}
							}
						},
						{
							"origin": [-23.5, 0.5, -47],
							"size": [47, 0, 40],
							"uv": {
								"up": {"uv": [247, 134], "uv_size": [-2, 35]},
								"down": {"uv": [245, 169], "uv_size": [2, -35]}
							}
						},
						{
							"origin": [31.5, 16.5, -47],
							"size": [8, 0, 40],
							"uv": {
								"up": {"uv": [245, 134], "uv_size": [2, 35]},
								"down": {"uv": [245, 169], "uv_size": [2, -35]}
							}
						},
						{
							"origin": [-39.5, 16.5, -47],
							"size": [8, 0, 40],
							"uv": {
								"up": {"uv": [245, 134], "uv_size": [2, 35]},
								"down": {"uv": [245, 169], "uv_size": [2, -35]}
							}
						},
						{
							"origin": [23.5, 8.5, -47],
							"size": [8, 0, 40],
							"uv": {
								"up": {"uv": [245, 134], "uv_size": [2, 35]},
								"down": {"uv": [245, 169], "uv_size": [2, -35]}
							}
						},
						{
							"origin": [-31.6, 8.5, -47],
							"size": [8, 0, 40],
							"uv": {
								"up": {"uv": [245, 134], "uv_size": [2, 35]},
								"down": {"uv": [245, 169], "uv_size": [2, -35]}
							}
						}
					]
				}
			]
		}
	]
}